gofile/__init__.py
gofile-0.2.0.dist-info/LICENSE
gofile-0.2.0.dist-info/METADATA
gofile-0.2.0.dist-info/WHEEL
gofile-0.2.0.dist-info/top_level.txt
gofile-0.2.0.dist-info/RECORD
