Metadata-Version: 2.1
Name: gofile
Version: 0.2.0
Summary: A simple Python wrapper for the GoFile API
Home-page: UNKNOWN
Author: Coosta6915
License: MIT
Project-URL: Documentation, https://github.com/Coosta6915/gofile/wiki/
Project-URL: GitHub, https://github.com/Coosta6915/gofile/
Platform: UNKNOWN
Classifier: Development Status :: 4 - Beta
Classifier: License :: OSI Approved :: MIT License
Classifier: Operating System :: OS Independent
Requires-Python: >=3
License-File: LICENSE
Requires-Dist: requests (~=2.25.1)
